{
  "Apple|iPhone 17 Pro Max|256 ГБ|SIM + eSIM|Blue": 111500,
  "Apple|iPhone 17 Pro Max|256 ГБ|SIM + eSIM|Orange": 110900,
  "Apple|iPhone 17 Pro Max|256 ГБ|SIM + eSIM|Silver": 111900,
  "Apple|iPhone 17 Pro Max|512 ГБ|SIM + eSIM|Blue": 128500,
  "Apple|iPhone 17 Pro Max|512 ГБ|SIM + eSIM|Orange": 127500,
  "Apple|iPhone 17 Pro Max|512 ГБ|SIM + eSIM|Silver": 132500,
  "Apple|iPhone 17 Pro|1 ТБ|SIM + eSIM|Blue": 138500,
  "Apple|iPhone 17 Pro|1 ТБ|SIM + eSIM|Silver": 138500,
  "Apple|iPhone 17 Pro|256 ГБ|SIM + eSIM|Blue": 102200,
  "Apple|iPhone 17 Pro|256 ГБ|SIM + eSIM|Silver": 102200,
  "Apple|iPhone 17 Pro|512 ГБ|SIM + eSIM|Blue": 117900,
  "Apple|iPhone 17 Pro|512 ГБ|SIM + eSIM|Orange": 115000,
  "Apple|iPhone 17 Pro|512 ГБ|SIM + eSIM|Silver": 116500,
  "Apple|iPhone 17e|256 ГБ|SIM + eSIM|Black": 58000,
  "Apple|iPhone 17e|256 ГБ|SIM + eSIM|Pink": 58000,
  "Apple|iPhone 17e|256 ГБ|SIM + eSIM|White": 58000,
  "Apple|iPhone 17|256 ГБ|SIM + eSIM|Black": 71900,
  "Apple|iPhone 17|256 ГБ|SIM + eSIM|Blue": 75500,
  "Apple|iPhone 17|256 ГБ|SIM + eSIM|White": 71900,
  "Apple|iPhone Air|256 ГБ|SIM + eSIM|Black": 76500,
  "Apple|iPhone Air|256 ГБ|SIM + eSIM|Gold": 75500,
  "Apple|iPhone Air|256 ГБ|SIM + eSIM|White": 76500
}
