{
  "Apple|iPhone 17 Pro Max|1 ТБ|SIM + eSIM|Blue": 147500,
  "Apple|iPhone 17 Pro Max|256 ГБ|SIM + eSIM|Blue": 111500,
  "Apple|iPhone 17 Pro Max|256 ГБ|SIM + eSIM|Orange": 107500,
  "Apple|iPhone 17 Pro Max|256 ГБ|SIM + eSIM|Silver": 112000,
  "Apple|iPhone 17 Pro Max|512 ГБ|SIM + eSIM|Blue": 127500,
  "Apple|iPhone 17 Pro|1 ТБ|SIM + eSIM|Blue": 136900,
  "Apple|iPhone 17 Pro|1 ТБ|SIM + eSIM|Silver": 136900,
  "Apple|iPhone 17 Pro|256 ГБ|SIM + eSIM|Blue": 102500,
  "Apple|iPhone 17 Pro|256 ГБ|SIM + eSIM|Orange": 100500,
  "Apple|iPhone 17 Pro|256 ГБ|SIM + eSIM|Silver": 102500,
  "Apple|iPhone 17 Pro|512 ГБ|SIM + eSIM|Blue": 116900,
  "Apple|iPhone 17 Pro|512 ГБ|SIM + eSIM|Orange": 115500,
  "Apple|iPhone 17 Pro|512 ГБ|SIM + eSIM|Silver": 117000,
  "Apple|iPhone 17e|256 ГБ|SIM + eSIM|Black": 58000,
  "Apple|iPhone 17e|256 ГБ|SIM + eSIM|Pink": 56000,
  "Apple|iPhone 17|256 ГБ|SIM + eSIM|Blue": 74500,
  "Apple|iPhone 17|256 ГБ|SIM + eSIM|Lavender": 72500,
  "Apple|iPhone 17|256 ГБ|SIM + eSIM|Sage": 72500,
  "Apple|iPhone Air|256 ГБ|SIM + eSIM|Black": 75500,
  "Apple|iPhone Air|256 ГБ|SIM + eSIM|Gold": 74500,
  "Apple|iPhone Air|256 ГБ|SIM + eSIM|White": 75500
}
